assets/fonts/onuava__.ttf
cli_client/__init__.py
cli_client/client.py
cli_client/config.py
cli_client/factory.py
exporter/__init__.py
exporter/abstracts.py
exporter/pdf_exporter.py
exporter/text_exporter.py
manager/__init__.py
manager/abstract.py
manager/manager.py
presenter/__init__.py
presenter/abstract.py
presenter/presenter.py
storage/__init__.py
storage/abstract.py
storage/factory.py
storage/io.py
storage/parser.py
storage/storage.py
tasks/__init__.py
tasks/abstract.py
tasks/errors.py
tasks/tasks.py
cli_task-0.2.0.dist-info/METADATA
cli_task-0.2.0.dist-info/WHEEL
cli_task-0.2.0.dist-info/entry_points.txt
cli_task-0.2.0.dist-info/top_level.txt
cli_task-0.2.0.dist-info/RECORD
