Metadata-Version: 2.1
Name: cli-task
Version: 0.2.0
Summary: A simple cli to-do list.
Home-page: https://github.com/aminFadaee/task
Author: Amin Fadaee
License: MIT
Platform: UNKNOWN
Classifier: License :: OSI Approved :: MIT License
Classifier: Programming Language :: Python :: 3
Classifier: Programming Language :: Python :: 3.8
Requires-Dist: click (==7.1.1)
Requires-Dist: fpdf (==1.7.2)
